odoo/addons/stock_picking_portal/README.rst
odoo/addons/stock_picking_portal/__init__.py
odoo/addons/stock_picking_portal/__manifest__.py
odoo/addons/stock_picking_portal/controllers/__init__.py
odoo/addons/stock_picking_portal/controllers/portal.py
odoo/addons/stock_picking_portal/data/demo.xml
odoo/addons/stock_picking_portal/i18n/it.po
odoo/addons/stock_picking_portal/i18n/stock_picking_portal.pot
odoo/addons/stock_picking_portal/models/__init__.py
odoo/addons/stock_picking_portal/models/res_config_settings.py
odoo/addons/stock_picking_portal/models/stock_picking.py
odoo/addons/stock_picking_portal/models/stock_picking_type.py
odoo/addons/stock_picking_portal/readme/CONFIGURE.rst
odoo/addons/stock_picking_portal/readme/CONTEXT.rst
odoo/addons/stock_picking_portal/readme/CONTRIBUTORS.rst
odoo/addons/stock_picking_portal/readme/DESCRIPTION.rst
odoo/addons/stock_picking_portal/readme/USAGE.rst
odoo/addons/stock_picking_portal/security/ir.model.access.csv
odoo/addons/stock_picking_portal/security/stock_picking_portal_rule.xml
odoo/addons/stock_picking_portal/static/description/icon.png
odoo/addons/stock_picking_portal/static/description/index.html
odoo/addons/stock_picking_portal/tests/__init__.py
odoo/addons/stock_picking_portal/tests/test_res_config_settings.py
odoo/addons/stock_picking_portal/tests/test_stock_picking_portal.py
odoo/addons/stock_picking_portal/tests/test_wizard.py
odoo/addons/stock_picking_portal/views/res_config_settings_view.xml
odoo/addons/stock_picking_portal/views/stock_picking_template.xml
odoo/addons/stock_picking_portal/wizards/__init__.py
odoo/addons/stock_picking_portal/wizards/picking_link_wizard.py
odoo/addons/stock_picking_portal/wizards/picking_link_wizard.xml
odoo_addon_stock_picking_portal-16.0.1.0.0.4.dist-info/METADATA
odoo_addon_stock_picking_portal-16.0.1.0.0.4.dist-info/WHEEL
odoo_addon_stock_picking_portal-16.0.1.0.0.4.dist-info/top_level.txt
odoo_addon_stock_picking_portal-16.0.1.0.0.4.dist-info/RECORD
